ultimatePSUR/__init__.py
ultimatePSUR/manager.py
ultimatePSUR/rotator.py
ultimatePSUR/scraper.py
ultimatePSUR-2.dist-info/METADATA
ultimatePSUR-2.dist-info/WHEEL
ultimatePSUR-2.dist-info/top_level.txt
ultimatePSUR-2.dist-info/RECORD
