Metadata-Version: 2.1
Name: ultimatePSUR
Version: 2
Summary: A powerful proxy scraper, updater, and rotator library
Home-page: https://github.com/Lixense/ultimatePSUR
Author: Lixense
Author-email: lixlix870@gmail.com
Classifier: Development Status :: 3 - Alpha
Classifier: Intended Audience :: Developers
Classifier: License :: OSI Approved :: MIT License
Classifier: Operating System :: OS Independent
Classifier: Programming Language :: Python :: 3
Classifier: Programming Language :: Python :: 3.7
Classifier: Programming Language :: Python :: 3.8
Classifier: Programming Language :: Python :: 3.9
Requires-Python: >=3.7
Requires-Dist: aiohttp
Requires-Dist: beautifulsoup4
Requires-Dist: requests
